smbus.so
smbus-1.1.post2.dist-info/DESCRIPTION.rst
smbus-1.1.post2.dist-info/METADATA
smbus-1.1.post2.dist-info/RECORD
smbus-1.1.post2.dist-info/WHEEL
smbus-1.1.post2.dist-info/metadata.json
smbus-1.1.post2.dist-info/top_level.txt
